LICENCE
MANIFEST.in
README.md
setup.py
cocktail_sort/__init__.py
cocktail_sort/examples.py
cocktail_sort/generate_random.py
cocktail_sort/main.py
cocktail_sort/sort_ascending.py
cocktail_sort/sort_descending.py
cocktail_sort/tests.py
cocktail_sort.egg-info/PKG-INFO
cocktail_sort.egg-info/SOURCES.txt
cocktail_sort.egg-info/dependency_links.txt
cocktail_sort.egg-info/entry_points.txt
cocktail_sort.egg-info/top_level.txt