Metadata-Version: 2.1
Name: cocktail-sort
Version: 1.2
Summary: cocktail_sorting
Home-page: UNKNOWN
Author: nazarbekov_1
Author-email: nazarbekov04@inbox.ru
License: MIT License
Platform: UNKNOWN
Requires-Python: >=3.5
License-File: LICENCE
